lspr/Nanoparticle.py
lspr/OpticalMaterial.py
lspr/Sellmeier.py
lspr/SpectralMeasurement.py
lspr/__init__.py
lspr-0.20.6.9.dist-info/LICENSE
lspr-0.20.6.9.dist-info/METADATA
lspr-0.20.6.9.dist-info/WHEEL
lspr-0.20.6.9.dist-info/top_level.txt
lspr-0.20.6.9.dist-info/RECORD
