Metadata-Version: 2.1
Name: lspr
Version: 0.20.6.9
Summary: lspr is a Python 3 scientific package for modelling UV-Vis spectral behaviour of metallic nanoparticle-dieletric composites.
Home-page: https://github.com/Arghantyr/LSPR-glass-transmittance
Author: Angantyr Krzysztof Orlinski
Author-email: kakoori@gmail.com
License: UNKNOWN
Platform: UNKNOWN
Classifier: Programming Language :: Python :: 3
Classifier: License :: OSI Approved :: MIT License
Classifier: Operating System :: OS Independent
Requires-Python: >=3.4
Requires-Dist: pandas (>=1.0.3)
Requires-Dist: numPy (>=1.18.1)
Requires-Dist: scipy (>=1.4.1)
Requires-Dist: statsmodels (>=0.11.0)
Requires-Dist: matplotlib (>=3.1.3)
